<?xml version="1.0" encoding="utf-8"?>
<source>
    <publisher>Facebook</publisher>
    <publisherurl>https://www.facebook.com/</publisherurl>
    <lastBuildDate>Mon, 09 Aug 2022 22:49:39 GMT</lastBuildDate>
    <job>
        <title><![CDATA[Package handler]]></title>
        <date><![CDATA[Tue, 29 Jun 2021 22:49:39 GMT]]></date>
        <referencenumber><![CDATA[UID01]]></referencenumber>
        <url>
            <![CDATA[http://www.examplesite.com/viewjob.cfm?jobid=UID01&amp;source=Indeed]]>
        </url>
        <company><![CDATA[UPS]]></company>
        <city><![CDATA[	West New York]]></city>
        <state><![CDATA[New Jersey]]></state>
        <radius><![CDATA[30]]></radius>
        <country><![CDATA[US]]></country>
        <postalcode><![CDATA[08817]]></postalcode>
        <streetaddress><![CDATA[FXG-US/USA/P072/Metuchen Hub]]></streetaddress>
        <email><![CDATA[example@abccorp.com]]></email>
        <description>
            <![CDATA[UPS is accepting applications for full-time Warehouse Delivery Drivers. This is a physical, fast-paced, outdoor position that involves continual lifting, lowering and carrying packages that typically weigh 25 - 35 lbs. and may weigh up to 70 lbs. A DOT physical exam is required. Warehouse Delivery Drivers must have excellent customer contact and driving skills. A minimum number of UPS facilities may require the ability to drive a delivery vehicle with a standard (manual) transmission. Qualified applicants must have a valid driver’s license issued in the state that they live in. Warehouse Delivery Drivers are expected to comply with UPS appearance guidelines and wear the company-provided uniform.

Full-time UPS employees work eight or more hours per day and workdays can vary (Tuesday - Saturday) or (Wednesday - Sunday) depending on the building needs. There is typically no available work on Monday’s for this position. Some work in the warehouse may be required.

What's in it for you? 

Excellent weekly pay
Safe work environment
401(k)
Medical, dental and vision after waiting period
And so much more
This job posting includes information about the minimum qualifications (including the UPS Uniform and Personal Appearance Guidelines), locations, shifts, and operations within the locations which may consider my application.  An applicant or employee may request an exception or change to, or an accommodation of, any condition of employment (including the UPS Uniform and Personal Appearance Guidelines) because of a sincerely held religious belief or practice.


UPS is an equal opportunity employer. UPS does not discriminate on the basis of race/color/religion/sex/national origin/veteran/disability/age/sexual orientation/gender identity or any other characteristic protected by law
]]>
        </description>
        <salary><![CDATA[5000 Monthly]]></salary>
        <education><![CDATA[N/A]]></education>
        <jobtype><![CDATA[Part Time]]></jobtype>
        <major_category><![CDATA[Transportation & Logistics]]></major_category>
        <minor_category><![CDATA[CDL A Local Company Driver]]></minor_category> 
        <requirements>
            <requirement1><![CDATA[Are you comfortable making multiple deliveries]]></requirement1>
			<requirement2><![CDATA[Are you comfortable lifting 50 lbs or more]]></requirement2>
        </requirements>
<?xml version="1.0" encoding="utf-8"?>
<source>
    <publisher>Facebook</publisher>
    <publisherurl>https://www.facebook.com/</publisherurl>
    <lastBuildDate>Mon, 09 Aug 2022 22:49:39 GMT</lastBuildDate>
    <job>
        <title><![CDATA[Package handler]]></title>
        <date><![CDATA[Tue, 29 Jun 2021 22:49:39 GMT]]></date>
        <referencenumber><![CDATA[UniqueID01]]></referencenumber>
        <url>
            <![CDATA[http://www.examplesite.com/viewjob.cfm?jobid=UniqueID01&amp;source=Indeed]]>
        </url>
        <company><![CDATA[Amazon]]></company>
        <city><![CDATA[	West New York]]></city>
        <state><![CDATA[New Jersey]]></state>
        <radius><![CDATA[30]]></radius>
        <country><![CDATA[US]]></country>
        <postalcode><![CDATA[08817]]></postalcode>
        <streetaddress><![CDATA[FXG-US/USA/P072/Metuchen Hub]]></streetaddress>
        <email><![CDATA[example@abccorp.com]]></email>
        <description>
            <![CDATA[IMMEDIATE OPENINGS!
Come for a job and stay for a career! FedEx Ground is part of the rapidly growing warehouse and transportation sector that helps keep America, and our economy, moving. Be part of a winning team and workplace community that cares about who you are as an individual, and your safety in the workplace.

Perks and Benefits at FedEx Ground

Competitive wages paid weekly for both full and part time opportunities

$5,250 tuition reimbursement every year with no lifetime cap! All employees are eligible for this awesome benefit on their first day of employment!

Generous paid time off program – work your way up to 5 weeks of PTO a year!

Medical, dental and vision benefits after a short waiting period.

Flexible scheduling that helps balance your work and personal life.

Valuable employee discounts on things like cell phone plans, electronics, cars and restaurants.

Free Purple Pathways career development program for all FedEx Ground employees.

Paid parental leave for both moms and dads!

Employee networks, and diversity, equity and inclusion programs available for all employees.

What you can expect at FedEx Ground:

Fast paced and physical warehouse work – why pay for a gym membership when you can get paid while working out?

Warehouse duties include loading, unloading, and sorting of packages of various sizes.

Part time FedEx Ground employees work one shift a day; full time FedEx Ground employees work two shifts.

Shift lengths vary based on package volume – generally part time employees work between 3 and 6 hours a day. Full time employees can expect to work between 6 and 10 hours.

Overtime paid after 40 hours a week.

Reasonable accommodations are available for qualified individuals with disabilities.]]>
        </description>
        <salary><![CDATA[5000 Monthly]]></salary>
        <education><![CDATA[N/A]]></education>
        <jobtype><![CDATA[Part Time]]></jobtype>
        <major_category><![CDATA[Transportation & Logistics]]></major_category>
        <minor_category><![CDATA[Driver Helper - Non CDL]]></minor_category> 
        <requirements>
            <requirement1><![CDATA[Able to lift 50 lbs]]></requirement1>
			<requirement2><![CDATA[Able to operate a forklift]]></requirement2>
        </requirements>
		<benefit>
			<benefit1><![CDATA[Health Care]]></benefit1>
			<benefit2><![CDATA[401k with Match]]></benefit2>
			<benefit3><![CDATA[Promote from Within]]></benefit3>
		</benefit>	
        <experience><![CDATA[5+ years]]></experience>
        <expirationdate><![CDATA[Tue, 08 Nov 2022]]></expirationdate>
        <remotetype><![CDATA[In Person]]></remotetype>
        <workschedule><![CDATA[]]></workschedule>
    </job>
      <job>
        <title><![CDATA[Package handler]]></title>
        <date><![CDATA[Tue, 29 Jun 2021 22:49:39 GMT]]></date>
        <referencenumber><![CDATA[UniqueID01]]></referencenumber>
        <url>
            <![CDATA[http://www.examplesite.com/viewjob.cfm?jobid=UniqueID01&amp;source=Indeed]]>
        </url>
        <company><![CDATA[Amazon]]></company>
        <city><![CDATA[Edison]]></city>
        <state><![CDATA[New Jersey]]></state>
        <radius><![CDATA[45]]></radius>
        <country><![CDATA[US]]></country>
        <postalcode><![CDATA[08817]]></postalcode>
        <streetaddress><![CDATA[FXG-US/USA/P072/Metuchen Hub]]></streetaddress>
        <email><![CDATA[example@abccorp.com]]></email>
        <description>
            <![CDATA[IMMEDIATE OPENINGS!
Come for a job and stay for a career! FedEx Ground is part of the rapidly growing warehouse and transportation sector that helps keep America, and our economy, moving. Be part of a winning team and workplace community that cares about who you are as an individual, and your safety in the workplace.

Perks and Benefits at FedEx Ground

Competitive wages paid weekly for both full and part time opportunities

$5,250 tuition reimbursement every year with no lifetime cap! All employees are eligible for this awesome benefit on their first day of employment!

Generous paid time off program – work your way up to 5 weeks of PTO a year!

Medical, dental and vision benefits after a short waiting period.

Flexible scheduling that helps balance your work and personal life.

Valuable employee discounts on things like cell phone plans, electronics, cars and restaurants.

Free Purple Pathways career development program for all FedEx Ground employees.

Paid parental leave for both moms and dads!

Employee networks, and diversity, equity and inclusion programs available for all employees.

What you can expect at FedEx Ground:

Fast paced and physical warehouse work – why pay for a gym membership when you can get paid while working out?

Warehouse duties include loading, unloading, and sorting of packages of various sizes.

Part time FedEx Ground employees work one shift a day; full time FedEx Ground employees work two shifts.

Shift lengths vary based on package volume – generally part time employees work between 3 and 6 hours a day. Full time employees can expect to work between 6 and 10 hours.

Overtime paid after 40 hours a week.

Reasonable accommodations are available for qualified individuals with disabilities.]]>
        </description>
        <salary><![CDATA[5000 Monthly]]></salary>
        <education><![CDATA[N/A]]></education>
        <jobtype><![CDATA[Part Time]]></jobtype>
        <major_category><![CDATA[Transportation & Logistics]]></major_category>
        <minor_category><![CDATA[Driver Helper - Non CDL]]></minor_category> 
        <requirements>
            <requirement1><![CDATA[Able to lift 50 lbs]]></requirement1>
			<requirement2><![CDATA[Able to operate a forklift]]></requirement2>
        </requirements>
		<benefit>
			<benefit1><![CDATA[Health Care]]></benefit1>
			<benefit2><![CDATA[401k with Match]]></benefit2>
			<benefit3><![CDATA[Promote from Within]]></benefit3>
		</benefit>	
        <experience><![CDATA[5+ years]]></experience>
        <expirationdate><![CDATA[Tue, 08 Nov 2022]]></expirationdate>
        <remotetype><![CDATA[In Person]]></remotetype>
        <workschedule><![CDATA[]]></workschedule>
    </job>
	    <job>
        <title><![CDATA[Package handler]]></title>
        <date><![CDATA[Tue, 29 Jun 2021 22:49:39 GMT]]></date>
        <referencenumber><![CDATA[UniqueID01]]></referencenumber>
        <url>
            <![CDATA[http://www.examplesite.com/viewjob.cfm?jobid=UniqueID01&amp;source=Indeed]]>
        </url>
        <company><![CDATA[Amazon]]></company>
        <city><![CDATA[New Brunswick]]></city>
        <state><![CDATA[New Jersey]]></state>
        <radius><![CDATA[45]]></radius>
        <country><![CDATA[US]]></country>
        <postalcode><![CDATA[08817]]></postalcode>
        <streetaddress><![CDATA[FXG-US/USA/P072/Metuchen Hub]]></streetaddress>
        <email><![CDATA[example@abccorp.com]]></email>
        <description>
            <![CDATA[IMMEDIATE OPENINGS!
Come for a job and stay for a career! FedEx Ground is part of the rapidly growing warehouse and transportation sector that helps keep America, and our economy, moving. Be part of a winning team and workplace community that cares about who you are as an individual, and your safety in the workplace.

Perks and Benefits at FedEx Ground

Competitive wages paid weekly for both full and part time opportunities

$5,250 tuition reimbursement every year with no lifetime cap! All employees are eligible for this awesome benefit on their first day of employment!

Generous paid time off program – work your way up to 5 weeks of PTO a year!

Medical, dental and vision benefits after a short waiting period.

Flexible scheduling that helps balance your work and personal life.

Valuable employee discounts on things like cell phone plans, electronics, cars and restaurants.

Free Purple Pathways career development program for all FedEx Ground employees.

Paid parental leave for both moms and dads!

Employee networks, and diversity, equity and inclusion programs available for all employees.

What you can expect at FedEx Ground:

Fast paced and physical warehouse work – why pay for a gym membership when you can get paid while working out?

Warehouse duties include loading, unloading, and sorting of packages of various sizes.

Part time FedEx Ground employees work one shift a day; full time FedEx Ground employees work two shifts.

Shift lengths vary based on package volume – generally part time employees work between 3 and 6 hours a day. Full time employees can expect to work between 6 and 10 hours.

Overtime paid after 40 hours a week.

Reasonable accommodations are available for qualified individuals with disabilities.]]>
        </description>
        <salary><![CDATA[5000 Monthly]]></salary>
        <education><![CDATA[N/A]]></education>
        <jobtype><![CDATA[Part Time]]></jobtype>
        <major_category><![CDATA[Transportation & Logistics]]></major_category>
        <minor_category><![CDATA[Driver Helper - Non CDL]]></minor_category> 
        <requirements>
            <requirement1><![CDATA[Able to lift 50 lbs]]></requirement1>
			<requirement2><![CDATA[Able to operate a forklift]]></requirement2>
        </requirements>
		<benefit>
			<benefit1><![CDATA[Health Care]]></benefit1>
			<benefit2><![CDATA[401k with Match]]></benefit2>
			<benefit3><![CDATA[Promote from Within]]></benefit3>
		</benefit>	
        <experience><![CDATA[5+ years]]></experience>
        <expirationdate><![CDATA[Tue, 08 Nov 2022]]></expirationdate>
        <remotetype><![CDATA[In Person]]></remotetype>
        <workschedule><![CDATA[]]></workschedule>
    </job>
	    <job>
        <title><![CDATA[Package handler]]></title>
        <date><![CDATA[Tue, 29 Jun 2021 22:49:39 GMT]]></date>
        <referencenumber><![CDATA[UniqueID02]]></referencenumber>
        <url>
            <![CDATA[http://www.examplesite.com/viewjob.cfm?jobid=UniqueID02&amp;source=Indeed]]>
        </url>
        <company><![CDATA[Amazon]]></company>
        <city><![CDATA[Newark]]></city>
        <state><![CDATA[Ohio]]></state>
        <radius><![CDATA[45]]></radius>
        <country><![CDATA[US]]></country>
        <postalcode><![CDATA[08817]]></postalcode>
        <streetaddress><![CDATA[FXG-US/USA/P072/Metuchen Hub]]></streetaddress>
        <email><![CDATA[example@abccorp.com]]></email>
        <description>
            <![CDATA[IMMEDIATE OPENINGS!
Come for a job and stay for a career! FedEx Ground is part of the rapidly growing warehouse and transportation sector that helps keep America, and our economy, moving. Be part of a winning team and workplace community that cares about who you are as an individual, and your safety in the workplace.

Perks and Benefits at FedEx Ground

Competitive wages paid weekly for both full and part time opportunities

$5,250 tuition reimbursement every year with no lifetime cap! All employees are eligible for this awesome benefit on their first day of employment!

Generous paid time off program – work your way up to 5 weeks of PTO a year!

Medical, dental and vision benefits after a short waiting period.

Flexible scheduling that helps balance your work and personal life.

Valuable employee discounts on things like cell phone plans, electronics, cars and restaurants.

Free Purple Pathways career development program for all FedEx Ground employees.

Paid parental leave for both moms and dads!

Employee networks, and diversity, equity and inclusion programs available for all employees.

What you can expect at FedEx Ground:

Fast paced and physical warehouse work – why pay for a gym membership when you can get paid while working out?

Warehouse duties include loading, unloading, and sorting of packages of various sizes.

Part time FedEx Ground employees work one shift a day; full time FedEx Ground employees work two shifts.

Shift lengths vary based on package volume – generally part time employees work between 3 and 6 hours a day. Full time employees can expect to work between 6 and 10 hours.

Overtime paid after 40 hours a week.

Reasonable accommodations are available for qualified individuals with disabilities.]]>
        </description>
        <salary><![CDATA[5000 Monthly]]></salary>
        <education><![CDATA[N/A]]></education>
        <jobtype><![CDATA[Part Time]]></jobtype>
        <major_category><![CDATA[Transportation & Logistics]]></major_category>
        <minor_category><![CDATA[Driver Helper - Non CDL]]></minor_category> 
        <requirements>
            <requirement1><![CDATA[Able to lift 50 lbs]]></requirement1>
			<requirement2><![CDATA[Able to operate a forklift]]></requirement2>
        </requirements>
		<benefit>
			<benefit1><![CDATA[Health Care]]></benefit1>
			<benefit2><![CDATA[401k with Match]]></benefit2>
			<benefit3><![CDATA[Promote from Within]]></benefit3>
		</benefit>	
        <experience><![CDATA[5+ years]]></experience>
        <expirationdate><![CDATA[Tue, 08 Nov 2022]]></expirationdate>
        <remotetype><![CDATA[In Person]]></remotetype>
        <workschedule><![CDATA[]]></workschedule>
    </job>
	    <job>
        <title><![CDATA[Package handler]]></title>
        <date><![CDATA[Tue, 29 Jun 2021 22:49:39 GMT]]></date>
        <referencenumber><![CDATA[UniqueID03]]></referencenumber>
        <url>
            <![CDATA[http://www.examplesite.com/viewjob.cfm?jobid=UniqueID03&amp;source=Indeed]]>
        </url>
        <company><![CDATA[Amazon]]></company>
        <city><![CDATA[Corona]]></city>
        <state><![CDATA[New York]]></state>
        <radius><![CDATA[45]]></radius>
        <country><![CDATA[US]]></country>
        <postalcode><![CDATA[08817]]></postalcode>
        <streetaddress><![CDATA[FXG-US/USA/P072/Metuchen Hub]]></streetaddress>
        <email><![CDATA[example@abccorp.com]]></email>
        <description>
            <![CDATA[IMMEDIATE OPENINGS!
Come for a job and stay for a career! FedEx Ground is part of the rapidly growing warehouse and transportation sector that helps keep America, and our economy, moving. Be part of a winning team and workplace community that cares about who you are as an individual, and your safety in the workplace.

Perks and Benefits at FedEx Ground

Competitive wages paid weekly for both full and part time opportunities

$5,250 tuition reimbursement every year with no lifetime cap! All employees are eligible for this awesome benefit on their first day of employment!

Generous paid time off program – work your way up to 5 weeks of PTO a year!

Medical, dental and vision benefits after a short waiting period.

Flexible scheduling that helps balance your work and personal life.

Valuable employee discounts on things like cell phone plans, electronics, cars and restaurants.

Free Purple Pathways career development program for all FedEx Ground employees.

Paid parental leave for both moms and dads!

Employee networks, and diversity, equity and inclusion programs available for all employees.

What you can expect at FedEx Ground:

Fast paced and physical warehouse work – why pay for a gym membership when you can get paid while working out?

Warehouse duties include loading, unloading, and sorting of packages of various sizes.

Part time FedEx Ground employees work one shift a day; full time FedEx Ground employees work two shifts.

Shift lengths vary based on package volume – generally part time employees work between 3 and 6 hours a day. Full time employees can expect to work between 6 and 10 hours.

Overtime paid after 40 hours a week.

Reasonable accommodations are available for qualified individuals with disabilities.]]>
        </description>
        <salary><![CDATA[5000 Monthly]]></salary>
        <education><![CDATA[N/A]]></education>
        <jobtype><![CDATA[Part Time]]></jobtype>
        <major_category><![CDATA[Transportation & Logistics]]></major_category>
        <minor_category><![CDATA[Driver Helper - Non CDL]]></minor_category> 
        <requirements>
            <requirement1><![CDATA[Able to lift 50 lbs]]></requirement1>
			<requirement2><![CDATA[Able to operate a forklift]]></requirement2>
        </requirements>
		<benefit>
			<benefit1><![CDATA[Health Care]]></benefit1>
			<benefit2><![CDATA[401k with Match]]></benefit2>
			<benefit3><![CDATA[Promote from Within]]></benefit3>
		</benefit>	
        <experience><![CDATA[5+ years]]></experience>
        <expirationdate><![CDATA[Tue, 08 Nov 2022]]></expirationdate>
        <remotetype><![CDATA[In Person]]></remotetype>
        <workschedule><![CDATA[]]></workschedule>
    </job>
	    <job>
        <title><![CDATA[Package handler]]></title>
        <date><![CDATA[Tue, 29 Jun 2021 22:49:39 GMT]]></date>
        <referencenumber><![CDATA[UniqueID04]]></referencenumber>
        <url>
            <![CDATA[http://www.examplesite.com/viewjob.cfm?jobid=UniqueID04&amp;source=Indeed]]>
        </url>
        <company><![CDATA[Amazon]]></company>
        <city><![CDATA[Katy]]></city>
        <state><![CDATA[New York]]></state>
        <radius><![CDATA[45]]></radius>
        <country><![CDATA[US]]></country>
        <postalcode><![CDATA[08817]]></postalcode>
        <streetaddress><![CDATA[FXG-US/USA/P072/Metuchen Hub]]></streetaddress>
        <email><![CDATA[example@abccorp.com]]></email>
        <description>
            <![CDATA[IMMEDIATE OPENINGS!
Come for a job and stay for a career! FedEx Ground is part of the rapidly growing warehouse and transportation sector that helps keep America, and our economy, moving. Be part of a winning team and workplace community that cares about who you are as an individual, and your safety in the workplace.

Perks and Benefits at FedEx Ground

Competitive wages paid weekly for both full and part time opportunities

$5,250 tuition reimbursement every year with no lifetime cap! All employees are eligible for this awesome benefit on their first day of employment!

Generous paid time off program – work your way up to 5 weeks of PTO a year!

Medical, dental and vision benefits after a short waiting period.

Flexible scheduling that helps balance your work and personal life.

Valuable employee discounts on things like cell phone plans, electronics, cars and restaurants.

Free Purple Pathways career development program for all FedEx Ground employees.

Paid parental leave for both moms and dads!

Employee networks, and diversity, equity and inclusion programs available for all employees.

What you can expect at FedEx Ground:

Fast paced and physical warehouse work – why pay for a gym membership when you can get paid while working out?

Warehouse duties include loading, unloading, and sorting of packages of various sizes.

Part time FedEx Ground employees work one shift a day; full time FedEx Ground employees work two shifts.

Shift lengths vary based on package volume – generally part time employees work between 3 and 6 hours a day. Full time employees can expect to work between 6 and 10 hours.

Overtime paid after 40 hours a week.

Reasonable accommodations are available for qualified individuals with disabilities.]]>
        </description>
        <salary><![CDATA[5000 Monthly]]></salary>
        <education><![CDATA[N/A]]></education>
        <jobtype><![CDATA[Part Time]]></jobtype>
        <major_category><![CDATA[Transportation & Logistics]]></major_category>
        <minor_category><![CDATA[Driver Helper - Non CDL]]></minor_category> 
        <requirements>
            <requirement1><![CDATA[Able to lift 50 lbs]]></requirement1>
			<requirement2><![CDATA[Able to operate a forklift]]></requirement2>
        </requirements>
		<benefit>
			<benefit1><![CDATA[Health Care]]></benefit1>
			<benefit2><![CDATA[401k with Match]]></benefit2>
			<benefit3><![CDATA[Promote from Within]]></benefit3>
		</benefit>	
        <experience><![CDATA[5+ years]]></experience>
        <expirationdate><![CDATA[Tue, 08 Nov 2022]]></expirationdate>
        <remotetype><![CDATA[In Person]]></remotetype>
        <workschedule><![CDATA[]]></workschedule>
    </job>
	    <job>
        <title><![CDATA[Package handler]]></title>
        <date><![CDATA[Tue, 29 Jun 2021 22:49:39 GMT]]></date>
        <referencenumber><![CDATA[UniqueID05]]></referencenumber>
        <url>
            <![CDATA[http://www.examplesite.com/viewjob.cfm?jobid=UniqueID05&amp;source=Indeed]]>
        </url>
        <company><![CDATA[Amazon]]></company>
        <city><![CDATA[South Gate]]></city>
        <state><![CDATA[California]]></state>
        <radius><![CDATA[45]]></radius>
        <country><![CDATA[US]]></country>
        <postalcode><![CDATA[08817]]></postalcode>
        <streetaddress><![CDATA[FXG-US/USA/P072/Metuchen Hub]]></streetaddress>
        <email><![CDATA[example@abccorp.com]]></email>
        <description>
            <![CDATA[IMMEDIATE OPENINGS!
Come for a job and stay for a career! FedEx Ground is part of the rapidly growing warehouse and transportation sector that helps keep America, and our economy, moving. Be part of a winning team and workplace community that cares about who you are as an individual, and your safety in the workplace.

Perks and Benefits at FedEx Ground

Competitive wages paid weekly for both full and part time opportunities

$5,250 tuition reimbursement every year with no lifetime cap! All employees are eligible for this awesome benefit on their first day of employment!

Generous paid time off program – work your way up to 5 weeks of PTO a year!

Medical, dental and vision benefits after a short waiting period.

Flexible scheduling that helps balance your work and personal life.

Valuable employee discounts on things like cell phone plans, electronics, cars and restaurants.

Free Purple Pathways career development program for all FedEx Ground employees.

Paid parental leave for both moms and dads!

Employee networks, and diversity, equity and inclusion programs available for all employees.

What you can expect at FedEx Ground:

Fast paced and physical warehouse work – why pay for a gym membership when you can get paid while working out?

Warehouse duties include loading, unloading, and sorting of packages of various sizes.

Part time FedEx Ground employees work one shift a day; full time FedEx Ground employees work two shifts.

Shift lengths vary based on package volume – generally part time employees work between 3 and 6 hours a day. Full time employees can expect to work between 6 and 10 hours.

Overtime paid after 40 hours a week.

Reasonable accommodations are available for qualified individuals with disabilities.]]>
        </description>
        <salary><![CDATA[5000 Monthly]]></salary>
        <education><![CDATA[N/A]]></education>
        <jobtype><![CDATA[Part Time]]></jobtype>
        <major_category><![CDATA[Transportation & Logistics]]></major_category>
        <minor_category><![CDATA[Driver Helper - Non CDL]]></minor_category> 
        <requirements>
            <requirement1><![CDATA[Able to lift 50 lbs]]></requirement1>
			<requirement2><![CDATA[Able to operate a forklift]]></requirement2>
        </requirements>
		<benefit>
			<benefit1><![CDATA[Health Care]]></benefit1>
			<benefit2><![CDATA[401k with Match]]></benefit2>
			<benefit3><![CDATA[Promote from Within]]></benefit3>
		</benefit>	
        <experience><![CDATA[5+ years]]></experience>
        <expirationdate><![CDATA[Tue, 08 Nov 2022]]></expirationdate>
        <remotetype><![CDATA[In Person]]></remotetype>
        <workschedule><![CDATA[]]></workschedule>
    </job>
	    <job>
        <title><![CDATA[Package handler]]></title>
        <date><![CDATA[Tue, 29 Jun 2021 22:49:39 GMT]]></date>
        <referencenumber><![CDATA[UniqueID06]]></referencenumber>
        <url>
            <![CDATA[http://www.examplesite.com/viewjob.cfm?jobid=UniqueID06&amp;source=Indeed]]>
        </url>
        <company><![CDATA[Amazon]]></company>
        <city><![CDATA[Edison]]></city>
        <state><![CDATA[New Jersey]]></state>
        <radius><![CDATA[45]]></radius>
        <country><![CDATA[US]]></country>
        <postalcode><![CDATA[08817]]></postalcode>
        <streetaddress><![CDATA[FXG-US/USA/P072/Metuchen Hub]]></streetaddress>
        <email><![CDATA[example@abccorp.com]]></email>
        <description>
            <![CDATA[IMMEDIATE OPENINGS!
Come for a job and stay for a career! FedEx Ground is part of the rapidly growing warehouse and transportation sector that helps keep America, and our economy, moving. Be part of a winning team and workplace community that cares about who you are as an individual, and your safety in the workplace.

Perks and Benefits at FedEx Ground

Competitive wages paid weekly for both full and part time opportunities

$5,250 tuition reimbursement every year with no lifetime cap! All employees are eligible for this awesome benefit on their first day of employment!

Generous paid time off program – work your way up to 5 weeks of PTO a year!

Medical, dental and vision benefits after a short waiting period.

Flexible scheduling that helps balance your work and personal life.

Valuable employee discounts on things like cell phone plans, electronics, cars and restaurants.

Free Purple Pathways career development program for all FedEx Ground employees.

Paid parental leave for both moms and dads!

Employee networks, and diversity, equity and inclusion programs available for all employees.

What you can expect at FedEx Ground:

Fast paced and physical warehouse work – why pay for a gym membership when you can get paid while working out?

Warehouse duties include loading, unloading, and sorting of packages of various sizes.

Part time FedEx Ground employees work one shift a day; full time FedEx Ground employees work two shifts.

Shift lengths vary based on package volume – generally part time employees work between 3 and 6 hours a day. Full time employees can expect to work between 6 and 10 hours.

Overtime paid after 40 hours a week.

Reasonable accommodations are available for qualified individuals with disabilities.]]>
        </description>
        <salary><![CDATA[5000 Monthly]]></salary>
        <education><![CDATA[N/A]]></education>
        <jobtype><![CDATA[Part Time]]></jobtype>
        <major_category><![CDATA[Transportation & Logistics]]></major_category>
        <minor_category><![CDATA[Driver Helper - Non CDL]]></minor_category> 
        <requirements>
            <requirement1><![CDATA[Able to lift 50 lbs]]></requirement1>
			<requirement2><![CDATA[Able to operate a forklift]]></requirement2>
        </requirements>
		<benefit>
			<benefit1><![CDATA[Health Care]]></benefit1>
			<benefit2><![CDATA[401k with Match]]></benefit2>
			<benefit3><![CDATA[Promote from Within]]></benefit3>
		</benefit>	
        <experience><![CDATA[5+ years]]></experience>
        <expirationdate><![CDATA[Tue, 08 Nov 2022]]></expirationdate>
        <remotetype><![CDATA[In Person]]></remotetype>
        <workschedule><![CDATA[]]></workschedule>
    </job>
	    <job>
        <title><![CDATA[Package handler]]></title>
        <date><![CDATA[Tue, 29 Jun 2021 22:49:39 GMT]]></date>
        <referencenumber><![CDATA[UniqueID07]]></referencenumber>
        <url>
            <![CDATA[http://www.examplesite.com/viewjob.cfm?jobid=UniqueID07&amp;source=Indeed]]>
        </url>
        <company><![CDATA[Amazon]]></company>
        <city><![CDATA[Lakewood]]></city>
        <state><![CDATA[New Jersey]]></state>
        <radius><![CDATA[45]]></radius>
        <country><![CDATA[US]]></country>
        <postalcode><![CDATA[08817]]></postalcode>
        <streetaddress><![CDATA[FXG-US/USA/P072/Metuchen Hub]]></streetaddress>
        <email><![CDATA[example@abccorp.com]]></email>
        <description>
            <![CDATA[IMMEDIATE OPENINGS!
Come for a job and stay for a career! FedEx Ground is part of the rapidly growing warehouse and transportation sector that helps keep America, and our economy, moving. Be part of a winning team and workplace community that cares about who you are as an individual, and your safety in the workplace.

Perks and Benefits at FedEx Ground

Competitive wages paid weekly for both full and part time opportunities

$5,250 tuition reimbursement every year with no lifetime cap! All employees are eligible for this awesome benefit on their first day of employment!

Generous paid time off program – work your way up to 5 weeks of PTO a year!

Medical, dental and vision benefits after a short waiting period.

Flexible scheduling that helps balance your work and personal life.

Valuable employee discounts on things like cell phone plans, electronics, cars and restaurants.

Free Purple Pathways career development program for all FedEx Ground employees.

Paid parental leave for both moms and dads!

Employee networks, and diversity, equity and inclusion programs available for all employees.

What you can expect at FedEx Ground:

Fast paced and physical warehouse work – why pay for a gym membership when you can get paid while working out?

Warehouse duties include loading, unloading, and sorting of packages of various sizes.

Part time FedEx Ground employees work one shift a day; full time FedEx Ground employees work two shifts.

Shift lengths vary based on package volume – generally part time employees work between 3 and 6 hours a day. Full time employees can expect to work between 6 and 10 hours.

Overtime paid after 40 hours a week.

Reasonable accommodations are available for qualified individuals with disabilities.]]>
        </description>
        <salary><![CDATA[5000 Monthly]]></salary>
        <education><![CDATA[N/A]]></education>
        <jobtype><![CDATA[Part Time]]></jobtype>
        <major_category><![CDATA[Transportation & Logistics]]></major_category>
        <minor_category><![CDATA[Driver Helper - Non CDL]]></minor_category> 
        <requirements>
            <requirement1><![CDATA[Able to lift 50 lbs]]></requirement1>
			<requirement2><![CDATA[Able to operate a forklift]]></requirement2>
        </requirements>
		<benefit>
			<benefit1><![CDATA[Health Care]]></benefit1>
			<benefit2><![CDATA[401k with Match]]></benefit2>
			<benefit3><![CDATA[Promote from Within]]></benefit3>
		</benefit>	
        <experience><![CDATA[5+ years]]></experience>
        <expirationdate><![CDATA[Tue, 08 Nov 2022]]></expirationdate>
        <remotetype><![CDATA[In Person]]></remotetype>
        <workschedule><![CDATA[]]></workschedule>
    </job>
	    <job>
        <title><![CDATA[Package handler]]></title>
        <date><![CDATA[Tue, 29 Jun 2021 22:49:39 GMT]]></date>
        <referencenumber><![CDATA[UniqueID08]]></referencenumber>
        <url>
            <![CDATA[http://www.examplesite.com/viewjob.cfm?jobid=UniqueID08&amp;source=Indeed]]>
        </url>
        <company><![CDATA[Amazon]]></company>
        <city><![CDATA[Bell Gardens]]></city>
        <state><![CDATA[California]]></state>
        <radius><![CDATA[45]]></radius>
        <country><![CDATA[US]]></country>
        <postalcode><![CDATA[08817]]></postalcode>
        <streetaddress><![CDATA[FXG-US/USA/P072/Metuchen Hub]]></streetaddress>
        <email><![CDATA[example@abccorp.com]]></email>
        <description>
            <![CDATA[IMMEDIATE OPENINGS!
Come for a job and stay for a career! FedEx Ground is part of the rapidly growing warehouse and transportation sector that helps keep America, and our economy, moving. Be part of a winning team and workplace community that cares about who you are as an individual, and your safety in the workplace.

Perks and Benefits at FedEx Ground

Competitive wages paid weekly for both full and part time opportunities

$5,250 tuition reimbursement every year with no lifetime cap! All employees are eligible for this awesome benefit on their first day of employment!

Generous paid time off program – work your way up to 5 weeks of PTO a year!

Medical, dental and vision benefits after a short waiting period.

Flexible scheduling that helps balance your work and personal life.

Valuable employee discounts on things like cell phone plans, electronics, cars and restaurants.

Free Purple Pathways career development program for all FedEx Ground employees.

Paid parental leave for both moms and dads!

Employee networks, and diversity, equity and inclusion programs available for all employees.

What you can expect at FedEx Ground:

Fast paced and physical warehouse work – why pay for a gym membership when you can get paid while working out?

Warehouse duties include loading, unloading, and sorting of packages of various sizes.

Part time FedEx Ground employees work one shift a day; full time FedEx Ground employees work two shifts.

Shift lengths vary based on package volume – generally part time employees work between 3 and 6 hours a day. Full time employees can expect to work between 6 and 10 hours.

Overtime paid after 40 hours a week.

Reasonable accommodations are available for qualified individuals with disabilities.]]>
        </description>
        <salary><![CDATA[5000 Monthly]]></salary>
        <education><![CDATA[N/A]]></education>
        <jobtype><![CDATA[Part Time]]></jobtype>
        <major_category><![CDATA[Transportation & Logistics]]></major_category>
        <minor_category><![CDATA[Driver Helper - Non CDL]]></minor_category> 
        <requirements>
            <requirement1><![CDATA[Able to lift 50 lbs]]></requirement1>
			<requirement2><![CDATA[Able to operate a forklift]]></requirement2>
        </requirements>
		<benefit>
			<benefit1><![CDATA[Health Care]]></benefit1>
			<benefit2><![CDATA[401k with Match]]></benefit2>
			<benefit3><![CDATA[Promote from Within]]></benefit3>
		</benefit>	
        <experience><![CDATA[5+ years]]></experience>
        <expirationdate><![CDATA[Tue, 08 Nov 2022]]></expirationdate>
        <remotetype><![CDATA[In Person]]></remotetype>
        <workschedule><![CDATA[]]></workschedule>
    </job>
	    <job>
        <title><![CDATA[Package handler]]></title>
        <date><![CDATA[Tue, 29 Jun 2021 22:49:39 GMT]]></date>
        <referencenumber><![CDATA[UniqueID09]]></referencenumber>
        <url>
            <![CDATA[http://www.examplesite.com/viewjob.cfm?jobid=UniqueID09&amp;source=Indeed]]>
        </url>
        <company><![CDATA[Amazon]]></company>
        <city><![CDATA[Texas City]]></city>
        <state><![CDATA[Texas]]></state>
        <radius><![CDATA[45]]></radius>
        <country><![CDATA[US]]></country>
        <postalcode><![CDATA[08817]]></postalcode>
        <streetaddress><![CDATA[FXG-US/USA/P072/Metuchen Hub]]></streetaddress>
        <email><![CDATA[example@abccorp.com]]></email>
        <description>
            <![CDATA[IMMEDIATE OPENINGS!
Come for a job and stay for a career! FedEx Ground is part of the rapidly growing warehouse and transportation sector that helps keep America, and our economy, moving. Be part of a winning team and workplace community that cares about who you are as an individual, and your safety in the workplace.

Perks and Benefits at FedEx Ground

Competitive wages paid weekly for both full and part time opportunities

$5,250 tuition reimbursement every year with no lifetime cap! All employees are eligible for this awesome benefit on their first day of employment!

Generous paid time off program – work your way up to 5 weeks of PTO a year!

Medical, dental and vision benefits after a short waiting period.

Flexible scheduling that helps balance your work and personal life.

Valuable employee discounts on things like cell phone plans, electronics, cars and restaurants.

Free Purple Pathways career development program for all FedEx Ground employees.

Paid parental leave for both moms and dads!

Employee networks, and diversity, equity and inclusion programs available for all employees.

What you can expect at FedEx Ground:

Fast paced and physical warehouse work – why pay for a gym membership when you can get paid while working out?

Warehouse duties include loading, unloading, and sorting of packages of various sizes.

Part time FedEx Ground employees work one shift a day; full time FedEx Ground employees work two shifts.

Shift lengths vary based on package volume – generally part time employees work between 3 and 6 hours a day. Full time employees can expect to work between 6 and 10 hours.

Overtime paid after 40 hours a week.

Reasonable accommodations are available for qualified individuals with disabilities.]]>
        </description>
        <salary><![CDATA[5000 Monthly]]></salary>
        <education><![CDATA[N/A]]></education>
        <jobtype><![CDATA[Part Time]]></jobtype>
        <major_category><![CDATA[Transportation & Logistics]]></major_category>
        <minor_category><![CDATA[Driver Helper - Non CDL]]></minor_category> 
        <requirements>
            <requirement1><![CDATA[Able to lift 50 lbs]]></requirement1>
			<requirement2><![CDATA[Able to operate a forklift]]></requirement2>
        </requirements>
		<benefit>
			<benefit1><![CDATA[Health Care]]></benefit1>
			<benefit2><![CDATA[401k with Match]]></benefit2>
			<benefit3><![CDATA[Promote from Within]]></benefit3>
		</benefit>	
        <experience><![CDATA[5+ years]]></experience>
        <expirationdate><![CDATA[Tue, 08 Nov 2022]]></expirationdate>
        <remotetype><![CDATA[In Person]]></remotetype>
        <workschedule><![CDATA[]]></workschedule>
    </job>
	    <job>
        <title><![CDATA[Package handler]]></title>
        <date><![CDATA[Tue, 29 Jun 2021 22:49:39 GMT]]></date>
        <referencenumber><![CDATA[UniqueID010]]></referencenumber>
        <url>
            <![CDATA[http://www.examplesite.com/viewjob.cfm?jobid=UniqueID01&amp;source=Indeed]]>
        </url>
        <company><![CDATA[Amazon]]></company>
        <city><![CDATA[Texarkana]]></city>
        <state><![CDATA[Texas]]></state>
        <radius><![CDATA[45]]></radius>
        <country><![CDATA[US]]></country>
        <postalcode><![CDATA[08817]]></postalcode>
        <streetaddress><![CDATA[FXG-US/USA/P072/Metuchen Hub]]></streetaddress>
        <email><![CDATA[example@abccorp.com]]></email>
        <description>
            <![CDATA[IMMEDIATE OPENINGS!
Come for a job and stay for a career! FedEx Ground is part of the rapidly growing warehouse and transportation sector that helps keep America, and our economy, moving. Be part of a winning team and workplace community that cares about who you are as an individual, and your safety in the workplace.

Perks and Benefits at FedEx Ground

Competitive wages paid weekly for both full and part time opportunities

$5,250 tuition reimbursement every year with no lifetime cap! All employees are eligible for this awesome benefit on their first day of employment!

Generous paid time off program – work your way up to 5 weeks of PTO a year!

Medical, dental and vision benefits after a short waiting period.

Flexible scheduling that helps balance your work and personal life.

Valuable employee discounts on things like cell phone plans, electronics, cars and restaurants.

Free Purple Pathways career development program for all FedEx Ground employees.

Paid parental leave for both moms and dads!

Employee networks, and diversity, equity and inclusion programs available for all employees.

What you can expect at FedEx Ground:

Fast paced and physical warehouse work – why pay for a gym membership when you can get paid while working out?

Warehouse duties include loading, unloading, and sorting of packages of various sizes.

Part time FedEx Ground employees work one shift a day; full time FedEx Ground employees work two shifts.

Shift lengths vary based on package volume – generally part time employees work between 3 and 6 hours a day. Full time employees can expect to work between 6 and 10 hours.

Overtime paid after 40 hours a week.

Reasonable accommodations are available for qualified individuals with disabilities.]]>
        </description>
        <salary><![CDATA[5000 Monthly]]></salary>
        <education><![CDATA[N/A]]></education>
        <jobtype><![CDATA[Part Time]]></jobtype>
        <major_category><![CDATA[Transportation & Logistics]]></major_category>
        <minor_category><![CDATA[Driver Helper - Non CDL]]></minor_category> 
        <requirements>
            <requirement1><![CDATA[Able to lift 50 lbs]]></requirement1>
			<requirement2><![CDATA[Able to operate a forklift]]></requirement2>
        </requirements>
		<benefit>
			<benefit1><![CDATA[Health Care]]></benefit1>
			<benefit2><![CDATA[401k with Match]]></benefit2>
			<benefit3><![CDATA[Promote from Within]]></benefit3>
		</benefit>	
        <experience><![CDATA[5+ years]]></experience>
        <expirationdate><![CDATA[Tue, 08 Nov 2022]]></expirationdate>
        <remotetype><![CDATA[In Person]]></remotetype>
        <workschedule><![CDATA[]]></workschedule>
</source>
        <experience><![CDATA[5+ years]]></experience>
        <expirationdate><![CDATA[Tue, 08 Nov 2022]]></expirationdate>
        <remotetype><![CDATA[In Person]]></remotetype>
        <workschedule><![CDATA[]]></workschedule>
    </job>
      <job>
        <title><![CDATA[Package handler]]></title>
        <date><![CDATA[Tue, 29 Jun 2021 22:49:39 GMT]]></date>
        <referencenumber><![CDATA[UID01]]></referencenumber>
        <url>
            <![CDATA[http://www.examplesite.com/viewjob.cfm?jobid=UID01&amp;source=Indeed]]>
        </url>
        <company><![CDATA[UPS]]></company>
        <city><![CDATA[Edison]]></city>
        <state><![CDATA[New Jersey]]></state>
        <radius><![CDATA[45]]></radius>
        <country><![CDATA[US]]></country>
        <postalcode><![CDATA[08817]]></postalcode>
        <streetaddress><![CDATA[FXG-US/USA/P072/Metuchen Hub]]></streetaddress>
        <email><![CDATA[example@abccorp.com]]></email>
        <description>
            <![CDATA[UPS is accepting applications for full-time Warehouse Delivery Drivers. This is a physical, fast-paced, outdoor position that involves continual lifting, lowering and carrying packages that typically weigh 25 - 35 lbs. and may weigh up to 70 lbs. A DOT physical exam is required. Warehouse Delivery Drivers must have excellent customer contact and driving skills. A minimum number of UPS facilities may require the ability to drive a delivery vehicle with a standard (manual) transmission. Qualified applicants must have a valid driver’s license issued in the state that they live in. Warehouse Delivery Drivers are expected to comply with UPS appearance guidelines and wear the company-provided uniform.

Full-time UPS employees work eight or more hours per day and workdays can vary (Tuesday - Saturday) or (Wednesday - Sunday) depending on the building needs. There is typically no available work on Monday’s for this position. Some work in the warehouse may be required.

What's in it for you? 

Excellent weekly pay
Safe work environment
401(k)
Medical, dental and vision after waiting period
And so much more
This job posting includes information about the minimum qualifications (including the UPS Uniform and Personal Appearance Guidelines), locations, shifts, and operations within the locations which may consider my application.  An applicant or employee may request an exception or change to, or an accommodation of, any condition of employment (including the UPS Uniform and Personal Appearance Guidelines) because of a sincerely held religious belief or practice.


UPS is an equal opportunity employer. UPS does not discriminate on the basis of race/color/religion/sex/national origin/veteran/disability/age/sexual orientation/gender identity or any other characteristic protected by law]]>
        </description>
        <salary><![CDATA[5000 Monthly]]></salary>
        <education><![CDATA[N/A]]></education>
        <jobtype><![CDATA[Part Time]]></jobtype>
        <major_category><![CDATA[Transportation & Logistics]]></major_category>
        <minor_category><![CDATA[CDL A Local Company Driver]]></minor_category> 
        <requirements>
            <requirement1><![CDATA[Are you comfortable making multiple deliveries]]></requirement1>
			<requirement2><![CDATA[Are you comfortable lifting 50 lbs or more]]></requirement2>
        </requirements>
		<benefit>
			<benefit1><![CDATA[Health Care]]></benefit1>
			<benefit2><![CDATA[401k with Match]]></benefit2>
			<benefit3><![CDATA[Promote from Within]]></benefit3>
		</benefit>	
        <experience><![CDATA[5+ years]]></experience>
        <expirationdate><![CDATA[Tue, 08 Nov 2022]]></expirationdate>
        <remotetype><![CDATA[In Person]]></remotetype>
        <workschedule><![CDATA[]]></workschedule>
    </job>
	    <job>
        <title><![CDATA[Package handler]]></title>
        <date><![CDATA[Tue, 29 Jun 2021 22:49:39 GMT]]></date>
        <referencenumber><![CDATA[UID01]]></referencenumber>
        <url>
            <![CDATA[http://www.examplesite.com/viewjob.cfm?jobid=UID01&amp;source=Indeed]]>
        </url>
        <company><![CDATA[UPS]]></company>
        <city><![CDATA[New Brunswick]]></city>
        <state><![CDATA[New Jersey]]></state>
        <radius><![CDATA[45]]></radius>
        <country><![CDATA[US]]></country>
        <postalcode><![CDATA[08817]]></postalcode>
        <streetaddress><![CDATA[FXG-US/USA/P072/Metuchen Hub]]></streetaddress>
        <email><![CDATA[example@abccorp.com]]></email>
       <description>
            <![CDATA[UPS is accepting applications for full-time Warehouse Delivery Drivers. This is a physical, fast-paced, outdoor position that involves continual lifting, lowering and carrying packages that typically weigh 25 - 35 lbs. and may weigh up to 70 lbs. A DOT physical exam is required. Warehouse Delivery Drivers must have excellent customer contact and driving skills. A minimum number of UPS facilities may require the ability to drive a delivery vehicle with a standard (manual) transmission. Qualified applicants must have a valid driver’s license issued in the state that they live in. Warehouse Delivery Drivers are expected to comply with UPS appearance guidelines and wear the company-provided uniform.

Full-time UPS employees work eight or more hours per day and workdays can vary (Tuesday - Saturday) or (Wednesday - Sunday) depending on the building needs. There is typically no available work on Monday’s for this position. Some work in the warehouse may be required.

What's in it for you? 

Excellent weekly pay
Safe work environment
401(k)
Medical, dental and vision after waiting period
And so much more
This job posting includes information about the minimum qualifications (including the UPS Uniform and Personal Appearance Guidelines), locations, shifts, and operations within the locations which may consider my application.  An applicant or employee may request an exception or change to, or an accommodation of, any condition of employment (including the UPS Uniform and Personal Appearance Guidelines) because of a sincerely held religious belief or practice.


UPS is an equal opportunity employer. UPS does not discriminate on the basis of race/color/religion/sex/national origin/veteran/disability/age/sexual orientation/gender identity or any other characteristic protected by law]]>
        </description>
        <salary><![CDATA[5000 Monthly]]></salary>
        <education><![CDATA[N/A]]></education>
        <jobtype><![CDATA[Part Time]]></jobtype>
        <major_category><![CDATA[Transportation & Logistics]]></major_category>
        <minor_category><![CDATA[CDL A Local Company Driver]]></minor_category> 
        <requirements>
            <requirement1><![CDATA[Are you comfortable making multiple deliveries]]></requirement1>
			<requirement2><![CDATA[Are you comfortable lifting 50 lbs or more]]></requirement2>
        </requirements>
		<benefit>
			<benefit1><![CDATA[Health Care]]></benefit1>
			<benefit2><![CDATA[401k with Match]]></benefit2>
			<benefit3><![CDATA[Promote from Within]]></benefit3>
		</benefit>	        <experience><![CDATA[5+ years]]></experience>
        <expirationdate><![CDATA[Tue, 08 Nov 2022]]></expirationdate>
        <remotetype><![CDATA[In Person]]></remotetype>
        <workschedule><![CDATA[]]></workschedule>
    </job>
	    <job>
        <title><![CDATA[Package handler]]></title>
        <date><![CDATA[Tue, 29 Jun 2021 22:49:39 GMT]]></date>
        <referencenumber><![CDATA[UID02]]></referencenumber>
        <url>
            <![CDATA[http://www.examplesite.com/viewjob.cfm?jobid=UID02&amp;source=Indeed]]>
        </url>
        <company><![CDATA[UPS]]></company>
        <city><![CDATA[Newark]]></city>
        <state><![CDATA[Ohio]]></state>
        <radius><![CDATA[45]]></radius>
        <country><![CDATA[US]]></country>
        <postalcode><![CDATA[08817]]></postalcode>
        <streetaddress><![CDATA[FXG-US/USA/P072/Metuchen Hub]]></streetaddress>
        <email><![CDATA[example@abccorp.com]]></email>
        <description>
            <![CDATA[UPS is accepting applications for full-time Warehouse Delivery Drivers. This is a physical, fast-paced, outdoor position that involves continual lifting, lowering and carrying packages that typically weigh 25 - 35 lbs. and may weigh up to 70 lbs. A DOT physical exam is required. Warehouse Delivery Drivers must have excellent customer contact and driving skills. A minimum number of UPS facilities may require the ability to drive a delivery vehicle with a standard (manual) transmission. Qualified applicants must have a valid driver’s license issued in the state that they live in. Warehouse Delivery Drivers are expected to comply with UPS appearance guidelines and wear the company-provided uniform.

Full-time UPS employees work eight or more hours per day and workdays can vary (Tuesday - Saturday) or (Wednesday - Sunday) depending on the building needs. There is typically no available work on Monday’s for this position. Some work in the warehouse may be required.

What's in it for you? 

Excellent weekly pay
Safe work environment
401(k)
Medical, dental and vision after waiting period
And so much more
This job posting includes information about the minimum qualifications (including the UPS Uniform and Personal Appearance Guidelines), locations, shifts, and operations within the locations which may consider my application.  An applicant or employee may request an exception or change to, or an accommodation of, any condition of employment (including the UPS Uniform and Personal Appearance Guidelines) because of a sincerely held religious belief or practice.


UPS is an equal opportunity employer. UPS does not discriminate on the basis of race/color/religion/sex/national origin/veteran/disability/age/sexual orientation/gender identity or any other characteristic protected by law]]>
        </description>
        <salary><![CDATA[5000 Monthly]]></salary>
        <education><![CDATA[N/A]]></education>
        <jobtype><![CDATA[Part Time]]></jobtype>
        <major_category><![CDATA[Transportation & Logistics]]></major_category>
        <minor_category><![CDATA[CDL A Local Company Driver]]></minor_category> 
        <requirements>
            <requirement1><![CDATA[Are you comfortable making multiple deliveries]]></requirement1>
			<requirement2><![CDATA[Are you comfortable lifting 50 lbs or more]]></requirement2>
        </requirements>
		<benefit>
			<benefit1><![CDATA[Health Care]]></benefit1>
			<benefit2><![CDATA[401k with Match]]></benefit2>
			<benefit3><![CDATA[Promote from Within]]></benefit3>
		</benefit>	
        <experience><![CDATA[5+ years]]></experience>
        <expirationdate><![CDATA[Tue, 08 Nov 2022]]></expirationdate>
        <remotetype><![CDATA[In Person]]></remotetype>
        <workschedule><![CDATA[]]></workschedule>
    </job>
	    <job>
        <title><![CDATA[Package handler]]></title>
        <date><![CDATA[Tue, 29 Jun 2021 22:49:39 GMT]]></date>
        <referencenumber><![CDATA[UID03]]></referencenumber>
        <url>
            <![CDATA[http://www.examplesite.com/viewjob.cfm?jobid=UID03&amp;source=Indeed]]>
        </url>
        <company><![CDATA[UPS]]></company>
        <city><![CDATA[Corona]]></city>
        <state><![CDATA[New York]]></state>
        <radius><![CDATA[45]]></radius>
        <country><![CDATA[US]]></country>
        <postalcode><![CDATA[08817]]></postalcode>
        <streetaddress><![CDATA[FXG-US/USA/P072/Metuchen Hub]]></streetaddress>
        <email><![CDATA[example@abccorp.com]]></email>
        <description>
            <![CDATA[UPS is accepting applications for full-time Warehouse Delivery Drivers. This is a physical, fast-paced, outdoor position that involves continual lifting, lowering and carrying packages that typically weigh 25 - 35 lbs. and may weigh up to 70 lbs. A DOT physical exam is required. Warehouse Delivery Drivers must have excellent customer contact and driving skills. A minimum number of UPS facilities may require the ability to drive a delivery vehicle with a standard (manual) transmission. Qualified applicants must have a valid driver’s license issued in the state that they live in. Warehouse Delivery Drivers are expected to comply with UPS appearance guidelines and wear the company-provided uniform.

Full-time UPS employees work eight or more hours per day and workdays can vary (Tuesday - Saturday) or (Wednesday - Sunday) depending on the building needs. There is typically no available work on Monday’s for this position. Some work in the warehouse may be required.

What's in it for you? 

Excellent weekly pay
Safe work environment
401(k)
Medical, dental and vision after waiting period
And so much more
This job posting includes information about the minimum qualifications (including the UPS Uniform and Personal Appearance Guidelines), locations, shifts, and operations within the locations which may consider my application.  An applicant or employee may request an exception or change to, or an accommodation of, any condition of employment (including the UPS Uniform and Personal Appearance Guidelines) because of a sincerely held religious belief or practice.


UPS is an equal opportunity employer. UPS does not discriminate on the basis of race/color/religion/sex/national origin/veteran/disability/age/sexual orientation/gender identity or any other characteristic protected by law]]>
        </description>
        <salary><![CDATA[5000 Monthly]]></salary>
        <education><![CDATA[N/A]]></education>
        <jobtype><![CDATA[Part Time]]></jobtype>
        <major_category><![CDATA[Transportation & Logistics]]></major_category>
        <minor_category><![CDATA[CDL A Local Company Driver]]></minor_category> 
        <requirements>
            <requirement1><![CDATA[Are you comfortable making multiple deliveries]]></requirement1>
			<requirement2><![CDATA[Are you comfortable lifting 50 lbs or more]]></requirement2>
        </requirements>
		<benefit>
			<benefit1><![CDATA[Health Care]]></benefit1>
			<benefit2><![CDATA[401k with Match]]></benefit2>
			<benefit3><![CDATA[Promote from Within]]></benefit3>
		</benefit>	
        <experience><![CDATA[5+ years]]></experience>
        <expirationdate><![CDATA[Tue, 08 Nov 2022]]></expirationdate>
        <remotetype><![CDATA[In Person]]></remotetype>
        <workschedule><![CDATA[]]></workschedule>
    </job>
	    <job>
        <title><![CDATA[Package handler]]></title>
        <date><![CDATA[Tue, 29 Jun 2021 22:49:39 GMT]]></date>
        <referencenumber><![CDATA[UID04]]></referencenumber>
        <url>
            <![CDATA[http://www.examplesite.com/viewjob.cfm?jobid=UID04&amp;source=Indeed]]>
        </url>
        <company><![CDATA[UPS]]></company>
        <city><![CDATA[Katy]]></city>
        <state><![CDATA[New York]]></state>
        <radius><![CDATA[45]]></radius>
        <country><![CDATA[US]]></country>
        <postalcode><![CDATA[08817]]></postalcode>
        <streetaddress><![CDATA[FXG-US/USA/P072/Metuchen Hub]]></streetaddress>
        <email><![CDATA[example@abccorp.com]]></email>
        <description>
            <![CDATA[UPS is accepting applications for full-time Warehouse Delivery Drivers. This is a physical, fast-paced, outdoor position that involves continual lifting, lowering and carrying packages that typically weigh 25 - 35 lbs. and may weigh up to 70 lbs. A DOT physical exam is required. Warehouse Delivery Drivers must have excellent customer contact and driving skills. A minimum number of UPS facilities may require the ability to drive a delivery vehicle with a standard (manual) transmission. Qualified applicants must have a valid driver’s license issued in the state that they live in. Warehouse Delivery Drivers are expected to comply with UPS appearance guidelines and wear the company-provided uniform.

Full-time UPS employees work eight or more hours per day and workdays can vary (Tuesday - Saturday) or (Wednesday - Sunday) depending on the building needs. There is typically no available work on Monday’s for this position. Some work in the warehouse may be required.

What's in it for you? 

Excellent weekly pay
Safe work environment
401(k)
Medical, dental and vision after waiting period
And so much more
This job posting includes information about the minimum qualifications (including the UPS Uniform and Personal Appearance Guidelines), locations, shifts, and operations within the locations which may consider my application.  An applicant or employee may request an exception or change to, or an accommodation of, any condition of employment (including the UPS Uniform and Personal Appearance Guidelines) because of a sincerely held religious belief or practice.


UPS is an equal opportunity employer. UPS does not discriminate on the basis of race/color/religion/sex/national origin/veteran/disability/age/sexual orientation/gender identity or any other characteristic protected by law]]>
        </description>
        <salary><![CDATA[5000 Monthly]]></salary>
        <education><![CDATA[N/A]]></education>
        <jobtype><![CDATA[Part Time]]></jobtype>
        <major_category><![CDATA[Transportation & Logistics]]></major_category>
        <minor_category><![CDATA[CDL A Local Company Driver]]></minor_category> 
        <requirements>
            <requirement1><![CDATA[Are you comfortable making multiple deliveries]]></requirement1>
			<requirement2><![CDATA[Are you comfortable lifting 50 lbs or more]]></requirement2>
        </requirements>
		<benefit>
			<benefit1><![CDATA[Health Care]]></benefit1>
			<benefit2><![CDATA[401k with Match]]></benefit2>
			<benefit3><![CDATA[Promote from Within]]></benefit3>
		</benefit>	
        <experience><![CDATA[5+ years]]></experience>
        <expirationdate><![CDATA[Tue, 08 Nov 2022]]></expirationdate>
        <remotetype><![CDATA[In Person]]></remotetype>
        <workschedule><![CDATA[]]></workschedule>
    </job>
	    <job>
        <title><![CDATA[Package handler]]></title>
        <date><![CDATA[Tue, 29 Jun 2021 22:49:39 GMT]]></date>
        <referencenumber><![CDATA[UID05]]></referencenumber>
        <url>
            <![CDATA[http://www.examplesite.com/viewjob.cfm?jobid=UID05&amp;source=Indeed]]>
        </url>
        <company><![CDATA[UPS]]></company>
        <city><![CDATA[South Gate]]></city>
        <state><![CDATA[California]]></state>
        <radius><![CDATA[45]]></radius>
        <country><![CDATA[US]]></country>
        <postalcode><![CDATA[08817]]></postalcode>
        <streetaddress><![CDATA[FXG-US/USA/P072/Metuchen Hub]]></streetaddress>
        <email><![CDATA[example@abccorp.com]]></email>
        <description>
            <![CDATA[UPS is accepting applications for full-time Warehouse Delivery Drivers. This is a physical, fast-paced, outdoor position that involves continual lifting, lowering and carrying packages that typically weigh 25 - 35 lbs. and may weigh up to 70 lbs. A DOT physical exam is required. Warehouse Delivery Drivers must have excellent customer contact and driving skills. A minimum number of UPS facilities may require the ability to drive a delivery vehicle with a standard (manual) transmission. Qualified applicants must have a valid driver’s license issued in the state that they live in. Warehouse Delivery Drivers are expected to comply with UPS appearance guidelines and wear the company-provided uniform.

Full-time UPS employees work eight or more hours per day and workdays can vary (Tuesday - Saturday) or (Wednesday - Sunday) depending on the building needs. There is typically no available work on Monday’s for this position. Some work in the warehouse may be required.

What's in it for you? 

Excellent weekly pay
Safe work environment
401(k)
Medical, dental and vision after waiting period
And so much more
This job posting includes information about the minimum qualifications (including the UPS Uniform and Personal Appearance Guidelines), locations, shifts, and operations within the locations which may consider my application.  An applicant or employee may request an exception or change to, or an accommodation of, any condition of employment (including the UPS Uniform and Personal Appearance Guidelines) because of a sincerely held religious belief or practice.


UPS is an equal opportunity employer. UPS does not discriminate on the basis of race/color/religion/sex/national origin/veteran/disability/age/sexual orientation/gender identity or any other characteristic protected by law]]>
        </description>
        <salary><![CDATA[5000 Monthly]]></salary>
        <education><![CDATA[N/A]]></education>
        <jobtype><![CDATA[Part Time]]></jobtype>
        <major_category><![CDATA[Transportation & Logistics]]></major_category>
        <minor_category><![CDATA[CDL A Local Company Driver]]></minor_category> 
        <requirements>
            <requirement1><![CDATA[Are you comfortable making multiple deliveries]]></requirement1>
			<requirement2><![CDATA[Are you comfortable lifting 50 lbs or more]]></requirement2>
        </requirements>
		<benefit>
			<benefit1><![CDATA[Health Care]]></benefit1>
			<benefit2><![CDATA[401k with Match]]></benefit2>
			<benefit3><![CDATA[Promote from Within]]></benefit3>
		</benefit>	
        <experience><![CDATA[5+ years]]></experience>
        <expirationdate><![CDATA[Tue, 08 Nov 2022]]></expirationdate>
        <remotetype><![CDATA[In Person]]></remotetype>
        <workschedule><![CDATA[]]></workschedule>
    </job>
	    <job>
        <title><![CDATA[Package handler]]></title>
        <date><![CDATA[Tue, 29 Jun 2021 22:49:39 GMT]]></date>
        <referencenumber><![CDATA[UID06]]></referencenumber>
        <url>
            <![CDATA[http://www.examplesite.com/viewjob.cfm?jobid=UID06&amp;source=Indeed]]>
        </url>
        <company><![CDATA[UPS]]></company>
        <city><![CDATA[Edison]]></city>
        <state><![CDATA[New Jersey]]></state>
        <radius><![CDATA[45]]></radius>
        <country><![CDATA[US]]></country>
        <postalcode><![CDATA[08817]]></postalcode>
        <streetaddress><![CDATA[FXG-US/USA/P072/Metuchen Hub]]></streetaddress>
        <email><![CDATA[example@abccorp.com]]></email>
        <description>
            <![CDATA[UPS is accepting applications for full-time Warehouse Delivery Drivers. This is a physical, fast-paced, outdoor position that involves continual lifting, lowering and carrying packages that typically weigh 25 - 35 lbs. and may weigh up to 70 lbs. A DOT physical exam is required. Warehouse Delivery Drivers must have excellent customer contact and driving skills. A minimum number of UPS facilities may require the ability to drive a delivery vehicle with a standard (manual) transmission. Qualified applicants must have a valid driver’s license issued in the state that they live in. Warehouse Delivery Drivers are expected to comply with UPS appearance guidelines and wear the company-provided uniform.

Full-time UPS employees work eight or more hours per day and workdays can vary (Tuesday - Saturday) or (Wednesday - Sunday) depending on the building needs. There is typically no available work on Monday’s for this position. Some work in the warehouse may be required.

What's in it for you? 

Excellent weekly pay
Safe work environment
401(k)
Medical, dental and vision after waiting period
And so much more
This job posting includes information about the minimum qualifications (including the UPS Uniform and Personal Appearance Guidelines), locations, shifts, and operations within the locations which may consider my application.  An applicant or employee may request an exception or change to, or an accommodation of, any condition of employment (including the UPS Uniform and Personal Appearance Guidelines) because of a sincerely held religious belief or practice.


UPS is an equal opportunity employer. UPS does not discriminate on the basis of race/color/religion/sex/national origin/veteran/disability/age/sexual orientation/gender identity or any other characteristic protected by law]]>
        </description>
        <salary><![CDATA[5000 Monthly]]></salary>
        <education><![CDATA[N/A]]></education>
        <jobtype><![CDATA[Part Time]]></jobtype>
        <major_category><![CDATA[Transportation & Logistics]]></major_category>
        <minor_category><![CDATA[CDL A Local Company Driver]]></minor_category> 
        <requirements>
            <requirement1><![CDATA[Are you comfortable making multiple deliveries]]></requirement1>
			<requirement2><![CDATA[Are you comfortable lifting 50 lbs or more]]></requirement2>
        </requirements>
		<benefit>
			<benefit1><![CDATA[Health Care]]></benefit1>
			<benefit2><![CDATA[401k with Match]]></benefit2>
			<benefit3><![CDATA[Promote from Within]]></benefit3>
		</benefit>	
        <experience><![CDATA[5+ years]]></experience>
        <expirationdate><![CDATA[Tue, 08 Nov 2022]]></expirationdate>
        <remotetype><![CDATA[In Person]]></remotetype>
        <workschedule><![CDATA[]]></workschedule>
    </job>
	    <job>
        <title><![CDATA[Package handler]]></title>
        <date><![CDATA[Tue, 29 Jun 2021 22:49:39 GMT]]></date>
        <referencenumber><![CDATA[UID07]]></referencenumber>
        <url>
            <![CDATA[http://www.examplesite.com/viewjob.cfm?jobid=UID07&amp;source=Indeed]]>
        </url>
        <company><![CDATA[UPS]]></company>
        <city><![CDATA[Lakewood]]></city>
        <state><![CDATA[New Jersey]]></state>
        <radius><![CDATA[45]]></radius>
        <country><![CDATA[US]]></country>
        <postalcode><![CDATA[08817]]></postalcode>
        <streetaddress><![CDATA[FXG-US/USA/P072/Metuchen Hub]]></streetaddress>
        <email><![CDATA[example@abccorp.com]]></email>
        <description>
            <![CDATA[UPS is accepting applications for full-time Warehouse Delivery Drivers. This is a physical, fast-paced, outdoor position that involves continual lifting, lowering and carrying packages that typically weigh 25 - 35 lbs. and may weigh up to 70 lbs. A DOT physical exam is required. Warehouse Delivery Drivers must have excellent customer contact and driving skills. A minimum number of UPS facilities may require the ability to drive a delivery vehicle with a standard (manual) transmission. Qualified applicants must have a valid driver’s license issued in the state that they live in. Warehouse Delivery Drivers are expected to comply with UPS appearance guidelines and wear the company-provided uniform.

Full-time UPS employees work eight or more hours per day and workdays can vary (Tuesday - Saturday) or (Wednesday - Sunday) depending on the building needs. There is typically no available work on Monday’s for this position. Some work in the warehouse may be required.

What's in it for you? 

Excellent weekly pay
Safe work environment
401(k)
Medical, dental and vision after waiting period
And so much more
This job posting includes information about the minimum qualifications (including the UPS Uniform and Personal Appearance Guidelines), locations, shifts, and operations within the locations which may consider my application.  An applicant or employee may request an exception or change to, or an accommodation of, any condition of employment (including the UPS Uniform and Personal Appearance Guidelines) because of a sincerely held religious belief or practice.


UPS is an equal opportunity employer. UPS does not discriminate on the basis of race/color/religion/sex/national origin/veteran/disability/age/sexual orientation/gender identity or any other characteristic protected by law]]>
        </description>
        <salary><![CDATA[5000 Monthly]]></salary>
        <education><![CDATA[N/A]]></education>
        <jobtype><![CDATA[Part Time]]></jobtype>
        <major_category><![CDATA[Transportation & Logistics]]></major_category>
        <minor_category><![CDATA[CDL A Local Company Driver]]></minor_category> 
        <requirements>
            <requirement1><![CDATA[Are you comfortable making multiple deliveries]]></requirement1>
			<requirement2><![CDATA[Are you comfortable lifting 50 lbs or more]]></requirement2>
        </requirements>
		<benefit>
			<benefit1><![CDATA[Health Care]]></benefit1>
			<benefit2><![CDATA[401k with Match]]></benefit2>
			<benefit3><![CDATA[Promote from Within]]></benefit3>
		</benefit>	
        <experience><![CDATA[5+ years]]></experience>
        <expirationdate><![CDATA[Tue, 08 Nov 2022]]></expirationdate>
        <remotetype><![CDATA[In Person]]></remotetype>
        <workschedule><![CDATA[]]></workschedule>
    </job>
	    <job>
        <title><![CDATA[Package handler]]></title>
        <date><![CDATA[Tue, 29 Jun 2021 22:49:39 GMT]]></date>
        <referencenumber><![CDATA[UID08]]></referencenumber>
        <url>
            <![CDATA[http://www.examplesite.com/viewjob.cfm?jobid=UID08&amp;source=Indeed]]>
        </url>
        <company><![CDATA[UPS]]></company>
        <city><![CDATA[Bell Gardens]]></city>
        <state><![CDATA[California]]></state>
        <radius><![CDATA[45]]></radius>
        <country><![CDATA[US]]></country>
        <postalcode><![CDATA[08817]]></postalcode>
        <streetaddress><![CDATA[FXG-US/USA/P072/Metuchen Hub]]></streetaddress>
        <email><![CDATA[example@abccorp.com]]></email>
        <description>
            <![CDATA[UPS is accepting applications for full-time Warehouse Delivery Drivers. This is a physical, fast-paced, outdoor position that involves continual lifting, lowering and carrying packages that typically weigh 25 - 35 lbs. and may weigh up to 70 lbs. A DOT physical exam is required. Warehouse Delivery Drivers must have excellent customer contact and driving skills. A minimum number of UPS facilities may require the ability to drive a delivery vehicle with a standard (manual) transmission. Qualified applicants must have a valid driver’s license issued in the state that they live in. Warehouse Delivery Drivers are expected to comply with UPS appearance guidelines and wear the company-provided uniform.

Full-time UPS employees work eight or more hours per day and workdays can vary (Tuesday - Saturday) or (Wednesday - Sunday) depending on the building needs. There is typically no available work on Monday’s for this position. Some work in the warehouse may be required.

What's in it for you? 

Excellent weekly pay
Safe work environment
401(k)
Medical, dental and vision after waiting period
And so much more
This job posting includes information about the minimum qualifications (including the UPS Uniform and Personal Appearance Guidelines), locations, shifts, and operations within the locations which may consider my application.  An applicant or employee may request an exception or change to, or an accommodation of, any condition of employment (including the UPS Uniform and Personal Appearance Guidelines) because of a sincerely held religious belief or practice.


UPS is an equal opportunity employer. UPS does not discriminate on the basis of race/color/religion/sex/national origin/veteran/disability/age/sexual orientation/gender identity or any other characteristic protected by law]]>
        </description>
        <salary><![CDATA[5000 Monthly]]></salary>
        <education><![CDATA[N/A]]></education>
        <jobtype><![CDATA[Part Time]]></jobtype>
        <major_category><![CDATA[Transportation & Logistics]]></major_category>
        <minor_category><![CDATA[CDL A Local Company Driver]]></minor_category> 
        <requirements>
            <requirement1><![CDATA[Are you comfortable making multiple deliveries]]></requirement1>
			<requirement2><![CDATA[Are you comfortable lifting 50 lbs or more]]></requirement2>
        </requirements>
		<benefit>
			<benefit1><![CDATA[Health Care]]></benefit1>
			<benefit2><![CDATA[401k with Match]]></benefit2>
			<benefit3><![CDATA[Promote from Within]]></benefit3>
		</benefit>	
        <experience><![CDATA[5+ years]]></experience>
        <expirationdate><![CDATA[Tue, 08 Nov 2022]]></expirationdate>
        <remotetype><![CDATA[In Person]]></remotetype>
        <workschedule><![CDATA[]]></workschedule>
    </job>
	    <job>
        <title><![CDATA[Package handler]]></title>
        <date><![CDATA[Tue, 29 Jun 2021 22:49:39 GMT]]></date>
        <referencenumber><![CDATA[UID09]]></referencenumber>
        <url>
            <![CDATA[http://www.examplesite.com/viewjob.cfm?jobid=UID09&amp;source=Indeed]]>
        </url>
        <company><![CDATA[UPS]]></company>
        <city><![CDATA[Texas City]]></city>
        <state><![CDATA[Texas]]></state>
        <radius><![CDATA[45]]></radius>
        <country><![CDATA[US]]></country>
        <postalcode><![CDATA[08817]]></postalcode>
        <streetaddress><![CDATA[FXG-US/USA/P072/Metuchen Hub]]></streetaddress>
        <email><![CDATA[example@abccorp.com]]></email>
        <description>
            <![CDATA[UPS is accepting applications for full-time Warehouse Delivery Drivers. This is a physical, fast-paced, outdoor position that involves continual lifting, lowering and carrying packages that typically weigh 25 - 35 lbs. and may weigh up to 70 lbs. A DOT physical exam is required. Warehouse Delivery Drivers must have excellent customer contact and driving skills. A minimum number of UPS facilities may require the ability to drive a delivery vehicle with a standard (manual) transmission. Qualified applicants must have a valid driver’s license issued in the state that they live in. Warehouse Delivery Drivers are expected to comply with UPS appearance guidelines and wear the company-provided uniform.

Full-time UPS employees work eight or more hours per day and workdays can vary (Tuesday - Saturday) or (Wednesday - Sunday) depending on the building needs. There is typically no available work on Monday’s for this position. Some work in the warehouse may be required.

What's in it for you? 

Excellent weekly pay
Safe work environment
401(k)
Medical, dental and vision after waiting period
And so much more
This job posting includes information about the minimum qualifications (including the UPS Uniform and Personal Appearance Guidelines), locations, shifts, and operations within the locations which may consider my application.  An applicant or employee may request an exception or change to, or an accommodation of, any condition of employment (including the UPS Uniform and Personal Appearance Guidelines) because of a sincerely held religious belief or practice.


UPS is an equal opportunity employer. UPS does not discriminate on the basis of race/color/religion/sex/national origin/veteran/disability/age/sexual orientation/gender identity or any other characteristic protected by law]]>
        </description>
        <salary><![CDATA[5000 Monthly]]></salary>
        <education><![CDATA[N/A]]></education>
        <jobtype><![CDATA[Part Time]]></jobtype>
        <major_category><![CDATA[Transportation & Logistics]]></major_category>
        <minor_category><![CDATA[CDL A Local Company Driver]]></minor_category> 
        <requirements>
            <requirement1><![CDATA[Are you comfortable making multiple deliveries]]></requirement1>
			<requirement2><![CDATA[Are you comfortable lifting 50 lbs or more]]></requirement2>
        </requirements>
		<benefit>
			<benefit1><![CDATA[Health Care]]></benefit1>
			<benefit2><![CDATA[401k with Match]]></benefit2>
			<benefit3><![CDATA[Promote from Within]]></benefit3>
		</benefit>	
        <experience><![CDATA[5+ years]]></experience>
        <expirationdate><![CDATA[Tue, 08 Nov 2022]]></expirationdate>
        <remotetype><![CDATA[In Person]]></remotetype>
        <workschedule><![CDATA[]]></workschedule>
    </job>
	    <job>
        <title><![CDATA[Package handler]]></title>
        <date><![CDATA[Tue, 29 Jun 2021 22:49:39 GMT]]></date>
        <referencenumber><![CDATA[UID010]]></referencenumber>
        <url>
            <![CDATA[http://www.examplesite.com/viewjob.cfm?jobid=UID01&amp;source=Indeed]]>
        </url>
        <company><![CDATA[UPS]]></company>
        <city><![CDATA[Texarkana]]></city>
        <state><![CDATA[Texas]]></state>
        <radius><![CDATA[45]]></radius>
        <country><![CDATA[US]]></country>
        <postalcode><![CDATA[08817]]></postalcode>
        <streetaddress><![CDATA[FXG-US/USA/P072/Metuchen Hub]]></streetaddress>
        <email><![CDATA[example@abccorp.com]]></email>
        <description>
            <![CDATA[UPS is accepting applications for full-time Warehouse Delivery Drivers. This is a physical, fast-paced, outdoor position that involves continual lifting, lowering and carrying packages that typically weigh 25 - 35 lbs. and may weigh up to 70 lbs. A DOT physical exam is required. Warehouse Delivery Drivers must have excellent customer contact and driving skills. A minimum number of UPS facilities may require the ability to drive a delivery vehicle with a standard (manual) transmission. Qualified applicants must have a valid driver’s license issued in the state that they live in. Warehouse Delivery Drivers are expected to comply with UPS appearance guidelines and wear the company-provided uniform.

Full-time UPS employees work eight or more hours per day and workdays can vary (Tuesday - Saturday) or (Wednesday - Sunday) depending on the building needs. There is typically no available work on Monday’s for this position. Some work in the warehouse may be required.

What's in it for you? 

Excellent weekly pay
Safe work environment
401(k)
Medical, dental and vision after waiting period
And so much more
This job posting includes information about the minimum qualifications (including the UPS Uniform and Personal Appearance Guidelines), locations, shifts, and operations within the locations which may consider my application.  An applicant or employee may request an exception or change to, or an accommodation of, any condition of employment (including the UPS Uniform and Personal Appearance Guidelines) because of a sincerely held religious belief or practice.


UPS is an equal opportunity employer. UPS does not discriminate on the basis of race/color/religion/sex/national origin/veteran/disability/age/sexual orientation/gender identity or any other characteristic protected by law]]>
        </description>
        <salary><![CDATA[5000 Monthly]]></salary>
        <education><![CDATA[N/A]]></education>
        <jobtype><![CDATA[Part Time]]></jobtype>
        <major_category><![CDATA[Transportation & Logistics]]></major_category>
        <minor_category><![CDATA[CDL A Local Company Driver]]></minor_category> 
        <requirements>
            <requirement1><![CDATA[Are you comfortable making multiple deliveries]]></requirement1>
			<requirement2><![CDATA[Are you comfortable lifting 50 lbs or more]]></requirement2>
        </requirements>
		<benefit>
			<benefit1><![CDATA[Health Care]]></benefit1>
			<benefit2><![CDATA[401k with Match]]></benefit2>
			<benefit3><![CDATA[Promote from Within]]></benefit3>
		</benefit>	
        <experience><![CDATA[5+ years]]></experience>
        <expirationdate><![CDATA[Tue, 08 Nov 2022]]></expirationdate>
        <remotetype><![CDATA[In Person]]></remotetype>
        <workschedule><![CDATA[]]></workschedule>
</source>
